{"message": "Found 270 records for AAPL",
    "results": [
        {
            "stockID": 3,
            "Date": "2022-05-27T00:00:00.000Z",
            "DateString": "27-MAY-2022",
            "Open": 145.389999,
            "High": 149.660004,
            "Low": 145.259995,
            "Close": 150.67,
            "Volume": 90575717
        },
        {
            "stockID": 3,
            "Date": "2022-05-26T00:00:00.000Z",
            "DateString": "26-MAY-2022",
            "Open": 137.389999,
            "High": 144.339996,
            "Low": 137.139999,
            "Close": 153.779999,
            "Volume": 90601500
        },
        {
            "stockID": 3,
            "Date": "2022-05-25T00:00:00.000Z",
            "DateString": "25-MAY-2022",
            "Open": 138.429993,
            "High": 141.789993,
            "Low": 138.339996,
            "Close": 140.520004,
            "Volume": 92482700
        },
        {
            "stockID": 3,
            "Date": "2022-05-24T00:00:00.000Z",
            "DateString": "24-MAY-2022",
            "Open": 140.809998,
            "High": 141.970001,
            "Low": 137.330002,
            "Close": 142.220001,
            "Volume": 104132700
        },
        {
            "stockID": 3,
            "Date": "2022-05-23T00:00:00.000Z",
            "DateString": "23-MAY-2022",
            "Open": 137.789993,
            "High": 143.259995,
            "Low": 137.649994,
            "Close": 145.110001,
            "Volume": 117726300
        },
        {
            "stockID": 3,
            "Date": "2022-05-20T00:00:00.000Z",
            "DateString": "20-MAY-2022",
            "Open": 139.089996,
            "High": 140.699997,
            "Low": 132.610001,
            "Close": 136.589996,
            "Volume": 137194600
        },
        {
            "stockID": 3,
            "Date": "2022-05-19T00:00:00.000Z",
            "DateString": "19-MAY-2022",
            "Open": 139.880005,
            "High": 141.660004,
            "Low": 136.600006,
            "Close": 135.350006,
            "Volume": 136095600
        },
        {
            "stockID": 3,
            "Date": "2022-05-18T00:00:00.000Z",
            "DateString": "18-MAY-2022",
            "Open": 146.850006,
            "High": 147.360001,
            "Low": 139.899994,
            "Close": 142.820007,
            "Volume": 109742900
        },
        {
            "stockID": 3,
            "Date": "2022-05-17T00:00:00.000Z",
            "DateString": "17-MAY-2022",
            "Open": 148.860001,
            "High": 149.770004,
            "Low": 146.679993,
            "Close": 148.240005,
            "Volume": 78336300
        },
        {
            "stockID": 3,
            "Date": "2022-05-16T00:00:00.000Z",
            "DateString": "16-MAY-2022",
            "Open": 145.550003,
            "High": 147.520004,
            "Low": 144.179993,
            "Close": 146.539993,
            "Volume": 86643800
        },
        {
            "stockID": 3,
            "Date": "2022-05-13T00:00:00.000Z",
            "DateString": "13-MAY-2022",
            "Open": 144.589996,
            "High": 148.100006,
            "Low": 143.110001,
            "Close": 148.110001,
            "Volume": 113787000
        },
        {
            "stockID": 3,
            "Date": "2022-05-12T00:00:00.000Z",
            "DateString": "12-MAY-2022",
            "Open": 142.770004,
            "High": 146.199997,
            "Low": 138.800003,
            "Close": 145.559998,
            "Volume": 182602000
        },
        {
            "stockID": 3,
            "Date": "2022-05-11T00:00:00.000Z",
            "DateString": "11-MAY-2022",
            "Open": 153.5,
            "High": 155.449997,
            "Low": 145.809998,
            "Close": 146.5,
            "Volume": 142689800
        },
        {
            "stockID": 3,
            "Date": "2022-05-10T00:00:00.000Z",
            "DateString": "10-MAY-2022",
            "Open": 155.520004,
            "High": 156.740005,
            "Low": 152.929993,
            "Close": 154.509995,
            "Volume": 115366700
        },
        {
            "stockID": 3,
            "Date": "2022-05-09T00:00:00.000Z",
            "DateString": "9-MAY-2022",
            "Open": 154.929993,
            "High": 155.830002,
            "Low": 151.490005,
            "Close": 152.059998,
            "Volume": 131577900
        },
        {
            "stockID": 3,
            "Date": "2022-05-06T00:00:00.000Z",
            "DateString": "6-MAY-2022",
            "Open": 156.009995,
            "High": 159.440002,
            "Low": 154.179993,
            "Close": 157.279999,
            "Volume": 116055700
        },
        {
            "stockID": 3,
            "Date": "2022-05-05T00:00:00.000Z",
            "DateString": "5-MAY-2022",
            "Open": 163.850006,
            "High": 164.080002,
            "Low": 154.949997,
            "Close": 156.770004,
            "Volume": 130525300
        },
        {
            "stockID": 3,
            "Date": "2022-05-04T00:00:00.000Z",
            "DateString": "4-MAY-2022",
            "Open": 159.669998,
            "High": 166.479996,
            "Low": 159.259995,
            "Close": 166.020004,
            "Volume": 108256500
        },
        {
            "stockID": 3,
            "Date": "2022-05-03T00:00:00.000Z",
            "DateString": "3-MAY-2022",
            "Open": 158.149994,
            "High": 160.710007,
            "Low": 156.320007,
            "Close": 159.479996,
            "Volume": 88966500
        },
        {
            "stockID": 3,
            "Date": "2022-05-02T00:00:00.000Z",
            "DateString": "2-MAY-2022",
            "Open": 156.710007,
            "High": 158.229996,
            "Low": 153.270004,
            "Close": 157.960007,
            "Volume": 123055300
        },
        {
            "stockID": 3,
            "Date": "2022-04-29T00:00:00.000Z",
            "DateString": "29-APR-2022",
            "Open": 161.839996,
            "High": 166.199997,
            "Low": 157.25,
            "Close": 157.649994,
            "Volume": 131587100
        },
        {
            "stockID": 3,
            "Date": "2022-04-28T00:00:00.000Z",
            "DateString": "28-APR-2022",
            "Open": 159.25,
            "High": 164.520004,
            "Low": 158.929993,
            "Close": 163.639999,
            "Volume": 130216800
        },
        {
            "stockID": 3,
            "Date": "2022-04-27T00:00:00.000Z",
            "DateString": "27-APR-2022",
            "Open": 155.910004,
            "High": 159.789993,
            "Low": 155.380005,
            "Close": 156.570007,
            "Volume": 88063200
        },
        {
            "stockID": 3,
            "Date": "2022-04-26T00:00:00.000Z",
            "DateString": "26-APR-2022",
            "Open": 162.25,
            "High": 162.339996,
            "Low": 156.720001,
            "Close": 156.800003,
            "Volume": 95623200
        },
        {
            "stockID": 3,
            "Date": "2022-04-25T00:00:00.000Z",
            "DateString": "25-APR-2022",
            "Open": 161.119995,
            "High": 163.169998,
            "Low": 158.460007,
            "Close": 162.880005,
            "Volume": 96046400
        },
        {
            "stockID": 3,
            "Date": "2022-04-22T00:00:00.000Z",
            "DateString": "22-APR-2022",
            "Open": 166.460007,
            "High": 167.869995,
            "Low": 161.5,
            "Close": 161.789993,
            "Volume": 84882400
        },
        {
            "stockID": 3,
            "Date": "2022-04-21T00:00:00.000Z",
            "DateString": "21-APR-2022",
            "Open": 168.910004,
            "High": 171.529999,
            "Low": 165.910004,
            "Close": 166.419998,
            "Volume": 87227800
        },
        {
            "stockID": 3,
            "Date": "2022-04-20T00:00:00.000Z",
            "DateString": "20-APR-2022",
            "Open": 168.759995,
            "High": 168.880005,
            "Low": 166.100006,
            "Close": 167.229996,
            "Volume": 67929800
        },
        {
            "stockID": 3,
            "Date": "2022-04-19T00:00:00.000Z",
            "DateString": "19-APR-2022",
            "Open": 165.020004,
            "High": 167.820007,
            "Low": 163.910004,
            "Close": 167.399994,
            "Volume": 67723800
        },
        {
            "stockID": 3,
            "Date": "2022-04-18T00:00:00.000Z",
            "DateString": "18-APR-2022",
            "Open": 163.919998,
            "High": 166.600006,
            "Low": 163.570007,
            "Close": 165.070007,
            "Volume": 69023900
        },
        {
            "stockID": 3,
            "Date": "2022-04-14T00:00:00.000Z",
            "DateString": "14-APR-2022",
            "Open": 170.619995,
            "High": 171.270004,
            "Low": 165.039993,
            "Close": 165.289993,
            "Volume": 75329400
        },
        {
            "stockID": 3,
            "Date": "2022-04-13T00:00:00.000Z",
            "DateString": "13-APR-2022",
            "Open": 167.389999,
            "High": 171.039993,
            "Low": 166.770004,
            "Close": 170.399994,
            "Volume": 70618900
        },
        {
            "stockID": 3,
            "Date": "2022-04-12T00:00:00.000Z",
            "DateString": "12-APR-2022",
            "Open": 168.020004,
            "High": 169.869995,
            "Low": 166.639999,
            "Close": 167.660004,
            "Volume": 79265200
        },
        {
            "stockID": 3,
            "Date": "2022-04-11T00:00:00.000Z",
            "DateString": "11-APR-2022",
            "Open": 168.710007,
            "High": 169.029999,
            "Low": 165.5,
            "Close": 165.75,
            "Volume": 72246700
        },
        {
            "stockID": 3,
            "Date": "2022-04-08T00:00:00.000Z",
            "DateString": "8-APR-2022",
            "Open": 171.779999,
            "High": 171.779999,
            "Low": 169.199997,
            "Close": 170.089996,
            "Volume": 76575500
        },
        {
            "stockID": 3,
            "Date": "2022-04-07T00:00:00.000Z",
            "DateString": "7-APR-2022",
            "Open": 171.160004,
            "High": 173.360001,
            "Low": 169.850006,
            "Close": 172.139999,
            "Volume": 77594700
        },
        {
            "stockID": 3,
            "Date": "2022-04-06T00:00:00.000Z",
            "DateString": "6-APR-2022",
            "Open": 172.360001,
            "High": 173.630005,
            "Low": 170.130005,
            "Close": 171.830002,
            "Volume": 89058800
        },
        {
            "stockID": 3,
            "Date": "2022-04-05T00:00:00.000Z",
            "DateString": "5-APR-2022",
            "Open": 177.5,
            "High": 178.300003,
            "Low": 174.419998,
            "Close": 175.059998,
            "Volume": 73401800
        },
        {
            "stockID": 3,
            "Date": "2022-04-04T00:00:00.000Z",
            "DateString": "4-APR-2022",
            "Open": 174.570007,
            "High": 178.490005,
            "Low": 174.440002,
            "Close": 178.440002,
            "Volume": 76468400
        },
        {
            "stockID": 3,
            "Date": "2022-04-01T00:00:00.000Z",
            "DateString": "1-APR-2022",
            "Open": 174.029999,
            "High": 174.880005,
            "Low": 171.940002,
            "Close": 174.309998,
            "Volume": 78751300
        },
        {
            "stockID": 3,
            "Date": "2022-03-31T00:00:00.000Z",
            "DateString": "31-MAR-2022",
            "Open": 177.839996,
            "High": 178.029999,
            "Low": 174.399994,
            "Close": 174.610001,
            "Volume": 103049300
        },
        {
            "stockID": 3,
            "Date": "2022-03-30T00:00:00.000Z",
            "DateString": "30-MAR-2022",
            "Open": 178.550003,
            "High": 179.610001,
            "Low": 176.699997,
            "Close": 177.770004,
            "Volume": 92633200
        },
        {
            "stockID": 3,
            "Date": "2022-03-29T00:00:00.000Z",
            "DateString": "29-MAR-2022",
            "Open": 176.690002,
            "High": 179.009995,
            "Low": 176.339996,
            "Close": 178.960007,
            "Volume": 100589400
        },
        {
            "stockID": 3,
            "Date": "2022-03-28T00:00:00.000Z",
            "DateString": "28-MAR-2022",
            "Open": 172.169998,
            "High": 175.729996,
            "Low": 172,
            "Close": 175.600006,
            "Volume": 90371900
        },
        {
            "stockID": 3,
            "Date": "2022-03-25T00:00:00.000Z",
            "DateString": "25-MAR-2022",
            "Open": 173.880005,
            "High": 175.279999,
            "Low": 172.75,
            "Close": 174.720001,
            "Volume": 80546200
        },
        {
            "stockID": 3,
            "Date": "2022-03-24T00:00:00.000Z",
            "DateString": "24-MAR-2022",
            "Open": 171.059998,
            "High": 174.139999,
            "Low": 170.210007,
            "Close": 174.070007,
            "Volume": 90131400
        },
        {
            "stockID": 3,
            "Date": "2022-03-23T00:00:00.000Z",
            "DateString": "23-MAR-2022",
            "Open": 167.990005,
            "High": 172.639999,
            "Low": 167.649994,
            "Close": 170.210007,
            "Volume": 98062700
        },
        {
            "stockID": 3,
            "Date": "2022-03-22T00:00:00.000Z",
            "DateString": "22-MAR-2022",
            "Open": 165.509995,
            "High": 169.419998,
            "Low": 164.910004,
            "Close": 168.820007,
            "Volume": 81532000
        },
        {
            "stockID": 3,
            "Date": "2022-03-21T00:00:00.000Z",
            "DateString": "21-MAR-2022",
            "Open": 163.509995,
            "High": 166.350006,
            "Low": 163.009995,
            "Close": 165.380005,
            "Volume": 95811400
        },
        {
            "stockID": 3,
            "Date": "2022-03-18T00:00:00.000Z",
            "DateString": "18-MAR-2022",
            "Open": 160.509995,
            "High": 164.479996,
            "Low": 159.759995,
            "Close": 163.979996,
            "Volume": 123511700
        },
        {
            "stockID": 3,
            "Date": "2022-03-17T00:00:00.000Z",
            "DateString": "17-MAR-2022",
            "Open": 158.610001,
            "High": 161,
            "Low": 157.630005,
            "Close": 160.619995,
            "Volume": 75615400
        },
        {
            "stockID": 3,
            "Date": "2022-03-16T00:00:00.000Z",
            "DateString": "16-MAR-2022",
            "Open": 157.050003,
            "High": 160,
            "Low": 154.460007,
            "Close": 159.589996,
            "Volume": 102300200
        },
        {
            "stockID": 3,
            "Date": "2022-03-15T00:00:00.000Z",
            "DateString": "15-MAR-2022",
            "Open": 150.899994,
            "High": 155.570007,
            "Low": 150.380005,
            "Close": 155.089996,
            "Volume": 92964300
        },
        {
            "stockID": 3,
            "Date": "2022-03-14T00:00:00.000Z",
            "DateString": "14-MAR-2022",
            "Open": 151.449997,
            "High": 154.119995,
            "Low": 150.100006,
            "Close": 150.619995,
            "Volume": 108732100
        },
        {
            "stockID": 3,
            "Date": "2022-03-11T00:00:00.000Z",
            "DateString": "11-MAR-2022",
            "Open": 158.929993,
            "High": 159.279999,
            "Low": 154.5,
            "Close": 154.729996,
            "Volume": 96970100
        },
        {
            "stockID": 3,
            "Date": "2022-03-10T00:00:00.000Z",
            "DateString": "10-MAR-2022",
            "Open": 160.199997,
            "High": 160.389999,
            "Low": 155.979996,
            "Close": 158.520004,
            "Volume": 105342000
        },
        {
            "stockID": 3,
            "Date": "2022-03-09T00:00:00.000Z",
            "DateString": "9-MAR-2022",
            "Open": 161.479996,
            "High": 163.410004,
            "Low": 159.410004,
            "Close": 162.949997,
            "Volume": 91454900
        },
        {
            "stockID": 3,
            "Date": "2022-03-08T00:00:00.000Z",
            "DateString": "8-MAR-2022",
            "Open": 158.820007,
            "High": 162.880005,
            "Low": 155.800003,
            "Close": 157.440002,
            "Volume": 131148300
        },
        {
            "stockID": 3,
            "Date": "2022-03-07T00:00:00.000Z",
            "DateString": "7-MAR-2022",
            "Open": 163.360001,
            "High": 165.020004,
            "Low": 159.039993,
            "Close": 159.300003,
            "Volume": 96418800
        },
        {
            "stockID": 3,
            "Date": "2022-03-04T00:00:00.000Z",
            "DateString": "4-MAR-2022",
            "Open": 164.490005,
            "High": 165.550003,
            "Low": 162.100006,
            "Close": 163.169998,
            "Volume": 83737200
        },
        {
            "stockID": 3,
            "Date": "2022-03-03T00:00:00.000Z",
            "DateString": "3-MAR-2022",
            "Open": 168.470001,
            "High": 168.910004,
            "Low": 165.550003,
            "Close": 166.229996,
            "Volume": 76678400
        },
        {
            "stockID": 3,
            "Date": "2022-03-02T00:00:00.000Z",
            "DateString": "2-MAR-2022",
            "Open": 164.389999,
            "High": 167.360001,
            "Low": 162.949997,
            "Close": 166.559998,
            "Volume": 79724800
        },
        {
            "stockID": 3,
            "Date": "2022-03-01T00:00:00.000Z",
            "DateString": "1-MAR-2022",
            "Open": 164.699997,
            "High": 166.600006,
            "Low": 161.970001,
            "Close": 163.199997,
            "Volume": 83474400
        },
        {
            "stockID": 3,
            "Date": "2022-02-28T00:00:00.000Z",
            "DateString": "28-FEB-2022",
            "Open": 163.059998,
            "High": 165.419998,
            "Low": 162.429993,
            "Close": 165.119995,
            "Volume": 95056600
        },
        {
            "stockID": 3,
            "Date": "2022-02-25T00:00:00.000Z",
            "DateString": "25-FEB-2022",
            "Open": 163.839996,
            "High": 165.119995,
            "Low": 160.869995,
            "Close": 164.850006,
            "Volume": 91974200
        },
        {
            "stockID": 3,
            "Date": "2022-02-24T00:00:00.000Z",
            "DateString": "24-FEB-2022",
            "Open": 152.580002,
            "High": 162.850006,
            "Low": 152,
            "Close": 162.740005,
            "Volume": 141147500
        },
        {
            "stockID": 3,
            "Date": "2022-02-23T00:00:00.000Z",
            "DateString": "23-FEB-2022",
            "Open": 165.539993,
            "High": 166.149994,
            "Low": 159.75,
            "Close": 160.070007,
            "Volume": 90009200
        },
        {
            "stockID": 3,
            "Date": "2022-02-22T00:00:00.000Z",
            "DateString": "22-FEB-2022",
            "Open": 164.979996,
            "High": 166.690002,
            "Low": 162.149994,
            "Close": 164.320007,
            "Volume": 91162800
        },
        {
            "stockID": 3,
            "Date": "2022-02-18T00:00:00.000Z",
            "DateString": "18-FEB-2022",
            "Open": 169.820007,
            "High": 170.539993,
            "Low": 166.190002,
            "Close": 167.300003,
            "Volume": 82772700
        },
        {
            "stockID": 3,
            "Date": "2022-02-17T00:00:00.000Z",
            "DateString": "17-FEB-2022",
            "Open": 171.029999,
            "High": 171.910004,
            "Low": 168.470001,
            "Close": 168.880005,
            "Volume": 69589300
        },
        {
            "stockID": 3,
            "Date": "2022-02-16T00:00:00.000Z",
            "DateString": "16-FEB-2022",
            "Open": 171.850006,
            "High": 173.339996,
            "Low": 170.050003,
            "Close": 172.550003,
            "Volume": 61177400
        },
        {
            "stockID": 3,
            "Date": "2022-02-15T00:00:00.000Z",
            "DateString": "15-FEB-2022",
            "Open": 170.970001,
            "High": 172.949997,
            "Low": 170.25,
            "Close": 172.789993,
            "Volume": 62527400
        },
        {
            "stockID": 3,
            "Date": "2022-02-14T00:00:00.000Z",
            "DateString": "14-FEB-2022",
            "Open": 167.369995,
            "High": 169.580002,
            "Low": 166.559998,
            "Close": 168.880005,
            "Volume": 86185500
        },
        {
            "stockID": 3,
            "Date": "2022-02-11T00:00:00.000Z",
            "DateString": "11-FEB-2022",
            "Open": 172.330002,
            "High": 173.080002,
            "Low": 168.039993,
            "Close": 168.639999,
            "Volume": 98670700
        }
    ]
}